pygrl/__init__.py
pygrl/custom_exception.py
pygrl/main.py
pygrl/storage.py
pygrl/storage/__init__.py
pygrl/storage/basic_storage.py
pygrl/storage/sqlite3_storage.py
pygrl/storage/storage.py
pygrl-0.0.6.5.dist-info/LICENSE
pygrl-0.0.6.5.dist-info/METADATA
pygrl-0.0.6.5.dist-info/WHEEL
pygrl-0.0.6.5.dist-info/top_level.txt
pygrl-0.0.6.5.dist-info/RECORD
