Metadata-Version: 2.1
Name: pygrl
Version: 0.0.6.5
Summary: Another Python package aim to offer "Rate Limiting" functionality for general use cases.
Home-page: UNKNOWN
Author: jonah_whaler_2348
Author-email: jk_saga@proton.me
License: MIT
Keywords: python,rate,limiter,rate limiter,rate limiting
Platform: UNKNOWN
Classifier: Development Status :: 1 - Planning
Classifier: Intended Audience :: Developers
Classifier: License :: OSI Approved :: MIT License
Classifier: Programming Language :: Python :: 3.10
License-File: LICENSE
